cliquematch/__init__.py
cliquematch/core.cpython-311-darwin.so
cliquematch/wrappers/l2lgraph.py
cliquematch/wrappers/__init__.py
cliquematch/wrappers/a2lgraph.py
cliquematch/wrappers/a2agraph.py
cliquematch/wrappers/l2agraph.py
cliquematch/wrappers/_gen_graph.py
cliquematch/wrappers/aligngraph.py
cliquematch/wrappers/isograph.py
cliquematch/core/core.h
cliquematch/core/pynwgraph.cpp
cliquematch/core/pyiterator.h
cliquematch/core/core.cpp
cliquematch/core/pynwgraph.h
cliquematch/core/pygraph.h
cliquematch/core/pyiterator.cpp
cliquematch/core/pygraph.cpp
cliquematch/core/wrap_pygraph.cpp
cliquematch/ext/eigen_wrap.h
cliquematch/ext/L2Lgraph.h
cliquematch/ext/ext.cpp
cliquematch/ext/A2Agraph.h
cliquematch/ext/Aligngraph.cpp
cliquematch/ext/A2Lgraph.cpp
cliquematch/ext/L2Lgraph.cpp
cliquematch/ext/L2Agraph.cpp
cliquematch/ext/Isograph.cpp
cliquematch/ext/Isograph.h
cliquematch/ext/eigen_distance.hpp
cliquematch/ext/A2Agraph.cpp
cliquematch/ext/Aligngraph.h
cliquematch/detail/utils.h
cliquematch/detail/mmio.cpp
cliquematch/detail/utils.cpp
cliquematch/detail/mmio.h
cliquematch/detail/gbits.h
cliquematch/detail/gbits.cpp
cliquematch/detail/nwgraph/nwgraph.cpp
cliquematch/detail/nwgraph/nw_dfs.cpp
cliquematch/detail/nwgraph/nwclique.cpp
cliquematch/detail/nwgraph/nwclique.h
cliquematch/detail/nwgraph/nw_enumerate.cpp
cliquematch/detail/nwgraph/wvertex.h
cliquematch/detail/nwgraph/nwgraph.h
cliquematch/detail/nwgraph/wvertex.cpp
cliquematch/detail/nwgraph/nw_heuristic.cpp
cliquematch/detail/graph/vertex.h
cliquematch/detail/graph/dfs.h
cliquematch/detail/graph/graph.cpp
cliquematch/detail/graph/clique.cpp
cliquematch/detail/graph/dfs_stack.cpp
cliquematch/detail/graph/searchstate.h
cliquematch/detail/graph/graph.h
cliquematch/detail/graph/heuristic.h
cliquematch/detail/graph/clique.h
cliquematch/detail/graph/dfs_recurse.cpp
cliquematch/detail/graph/heuristic.cpp
cliquematch/detail/graph/enumerate.cpp
cliquematch-3.0.1.dist-info/RECORD
cliquematch-3.0.1.dist-info/LICENSE
cliquematch-3.0.1.dist-info/WHEEL
cliquematch-3.0.1.dist-info/top_level.txt
cliquematch-3.0.1.dist-info/METADATA
