Metadata-Version: 2.1
Name: cliquematch
Version: 3.0.1
Summary: Finding correspondence via maximum cliques in large graphs
Home-page: https://github.com/ahgamut/cliquematch
Author: Gautham
Author-email: ahgamut@gmail.com
License: MIT License
Project-URL: Homepage, https://github.com/ahgamut/cliquematch
Project-URL: Documentation, https://cliquematch.rtfd.io
Project-URL: Issues, https://github.com/ahgamut/cliquematch/issues
Classifier: Programming Language :: Python :: 3
Classifier: License :: OSI Approved :: MIT License
Classifier: Operating System :: OS Independent
Requires-Python: >=3.7
License-File: LICENSE
Requires-Dist: numpy >=1.14
Requires-Dist: pybind11 >=2.2
